README.md
setup.py
Decision_tree_zrq_1.egg-info/PKG-INFO
Decision_tree_zrq_1.egg-info/SOURCES.txt
Decision_tree_zrq_1.egg-info/dependency_links.txt
Decision_tree_zrq_1.egg-info/top_level.txt
neupy_core_model_api_src/Decision_tree.py
neupy_core_model_api_src/__init__.py
neupy_core_model_api_src/chiMerge.py
rsources/__init__.py
scripts/__init__.py